vumi_twilio_api/twiml_parser.py
vumi_twilio_api/__init__.py
vumi_twilio_api/twilio_api.py
vumi_twilio_api/tests/test_twiml_parser.py
vumi_twilio_api/tests/helpers.py
vumi_twilio_api/tests/__init__.py
vumi_twilio_api/tests/test_twilio_api.py
vxtwinio/twiml_parser.py
vxtwinio/__init__.py
vxtwinio/twilio_api.py
vxtwinio/tests/test_twiml_parser.py
vxtwinio/tests/helpers.py
vxtwinio/tests/__init__.py
vxtwinio/tests/test_twilio_api.py
vxtwinio-0.0.4.dist-info/METADATA
vxtwinio-0.0.4.dist-info/RECORD
vxtwinio-0.0.4.dist-info/top_level.txt
vxtwinio-0.0.4.dist-info/metadata.json
vxtwinio-0.0.4.dist-info/WHEEL
vxtwinio-0.0.4.dist-info/DESCRIPTION.rst
