Metadata-Version: 2.0
Name: vxtwinio
Version: 0.0.4
Summary: Provides a REST API to Vumi that emulates the Twilio API
Home-page: https://github.com/praekelt/vumi-twilio-api
Author: Praekelt Foundation
Author-email: dev@praekeltfoundation.org
License: BSD
Platform: UNKNOWN
Classifier: Development Status :: 4 - Beta
Classifier: Intended Audience :: Developers
Classifier: License :: OSI Approved :: BSD License
Classifier: Operating System :: POSIX
Classifier: Programming Language :: Python
Classifier: Programming Language :: Python :: 2.6
Classifier: Programming Language :: Python :: 2.7
Classifier: Topic :: Software Development :: Libraries :: Python Modules
Classifier: Topic :: System :: Networking
Requires-Dist: vumi
Requires-Dist: klein
Requires-Dist: treq
